fast_clean_architecture/__init__.py
fast_clean_architecture/__main__.py
fast_clean_architecture/analytics.py
fast_clean_architecture/cli.py
fast_clean_architecture/config.py
fast_clean_architecture/error_tracking.py
fast_clean_architecture/exceptions.py
fast_clean_architecture/health.py
fast_clean_architecture/logging_config.py
fast_clean_architecture/metrics.py
fast_clean_architecture/protocols.py
fast_clean_architecture/utils.py
fast_clean_architecture/validation.py
fast_clean_architecture/generators/__init__.py
fast_clean_architecture/generators/component_generator.py
fast_clean_architecture/generators/config_updater.py
fast_clean_architecture/generators/generator_factory.py
fast_clean_architecture/generators/package_generator.py
fast_clean_architecture/generators/template_validator.py
fast_clean_architecture/generators/validation_config.py
fast_clean_architecture/generators/validation_metrics.py
fast_clean_architecture/templates/__init__.py
fast_clean_architecture/templates/__init__.py.j2
fast_clean_architecture/templates/api.py.j2
fast_clean_architecture/templates/command.py.j2
fast_clean_architecture/templates/dto.py.j2
fast_clean_architecture/templates/entity.py.j2
fast_clean_architecture/templates/enum.py.j2
fast_clean_architecture/templates/enum_api.py.j2
fast_clean_architecture/templates/enum_full.py.j2
fast_clean_architecture/templates/enum_simple.py.j2
fast_clean_architecture/templates/event.py.j2
fast_clean_architecture/templates/exception.py.j2
fast_clean_architecture/templates/external.py.j2
fast_clean_architecture/templates/infrastructure_repository.py.j2
fast_clean_architecture/templates/interface.py.j2
fast_clean_architecture/templates/model.py.j2
fast_clean_architecture/templates/query.py.j2
fast_clean_architecture/templates/repository.py.j2
fast_clean_architecture/templates/schemas.py.j2
fast_clean_architecture/templates/service.py.j2
fast_clean_architecture/templates/value_object.py.j2
fast_clean_architecture-2.0.0.dist-info/METADATA
fast_clean_architecture-2.0.0.dist-info/WHEEL
fast_clean_architecture-2.0.0.dist-info/entry_points.txt
fast_clean_architecture-2.0.0.dist-info/licenses/LICENSE
fast_clean_architecture-2.0.0.dist-info/RECORD
