Metadata-Version: 2.4
Name: fast-clean-architecture
Version: 2.0.0
Summary: CLI tool for scaffolding clean architecture in FastAPI projects
Project-URL: Homepage, https://github.com/alden-technologies/fast-clean-architecture
Project-URL: Repository, https://github.com/alden-technologies/fast-clean-architecture
Project-URL: Documentation, https://fast-clean-architecture.readthedocs.io
Project-URL: Bug Tracker, https://github.com/alden-technologies/fast-clean-architecture/issues
Project-URL: Changelog, https://github.com/alden-technologies/fast-clean-architecture/blob/main/CHANGELOG.md
Author-email: Adegbenga Agoro <adegbenga@aldentechnologies.com>
License: MIT
License-File: LICENSE
Keywords: clean-architecture,cli,ddd,domain-driven-design,fastapi,scaffold
Classifier: Development Status :: 5 - Production/Stable
Classifier: Framework :: FastAPI
Classifier: Intended Audience :: Developers
Classifier: License :: OSI Approved :: MIT License
Classifier: Operating System :: OS Independent
Classifier: Programming Language :: Python :: 3
Classifier: Programming Language :: Python :: 3.9
Classifier: Programming Language :: Python :: 3.10
Classifier: Programming Language :: Python :: 3.11
Classifier: Programming Language :: Python :: 3.12
Classifier: Topic :: Software Development :: Code Generators
Classifier: Topic :: Software Development :: Libraries :: Application Frameworks
Requires-Python: >=3.9
Requires-Dist: jinja2<4.0.0,>=3.1.0
Requires-Dist: pathlib-mate<2.0.0,>=1.0.0
Requires-Dist: portalocker<3.0.0,>=2.0.0
Requires-Dist: psutil>=5.9.0
Requires-Dist: pydantic<3.0.0,>=2.0.0
Requires-Dist: pyyaml<7.0.0,>=6.0
Requires-Dist: rich<14.0.0,>=13.0.0
Requires-Dist: structlog<24.0.0,>=23.0.0
Requires-Dist: tomli>=1.2.0; python_version < '3.11'
Requires-Dist: typer[all]<1.0.0,>=0.9.0
